shunya/__init__.py
shunya/cli.py
shunya/shunya.py
shunya-0.0.1.dist-info/AUTHORS.rst
shunya-0.0.1.dist-info/LICENSE
shunya-0.0.1.dist-info/METADATA
shunya-0.0.1.dist-info/WHEEL
shunya-0.0.1.dist-info/entry_points.txt
shunya-0.0.1.dist-info/top_level.txt
shunya-0.0.1.dist-info/RECORD
