Metadata-Version: 2.1
Name: shunya
Version: 0.0.1
Summary: Shunya is all about creating something from nothing, a blank slate per se with some helpers on adrenaline
Home-page: https://github.com/chinmaysjoshi/shunya
Author: Chinmay Shrinivas Joshi
Author-email: chinmaysjoshi@gmail.com
License: MIT license
Keywords: shunya
Platform: UNKNOWN
Classifier: Development Status :: 2 - Pre-Alpha
Classifier: Intended Audience :: Developers
Classifier: License :: OSI Approved :: MIT License
Classifier: Natural Language :: English
Classifier: Programming Language :: Python :: 3
Classifier: Programming Language :: Python :: 3.6
Classifier: Programming Language :: Python :: 3.7
Classifier: Programming Language :: Python :: 3.8
Requires-Python: >=3.6
License-File: LICENSE
License-File: AUTHORS.rst
Requires-Dist: Click (>=7.0)
